{
  "container": {
    "background": {
      "base": {
        "$*": {
          "fill": "#183a37"
        },
        "$hover": {
          "fill": "#1f3f6b"
        },
        "padding": {
          "$*": [0, 40]
        }
      }
    },
    "border": {
      "base": {
        "color": {
          "$*": "#183a37"
        },
        "width": {
          "$hover": 1
        },
        "$hover": {
          "color": "#4f78ad"
        },
        "radius": {
          "$*": 24
        }
      }
    }
  },
  "label": {
    "base": {
      "font": {
        "color": {
          "$*": "#f7f4ea"
        }
      }
    }
  },
  "icon": {
    "base": {
      "size": {
        "width": {
          "$*": 24
        },
        "height": {
          "$*": 24
        }
      }
    }
  }
}
